{
  "type": "Feature",
  "properties": {
    "gn:asciiname":"Leoville",
    "gn:country_code":"JE",
    "gn:dem":93,
    "gn:feature_class":"P",
    "gn:feature_code":"PPL",
    "gn:name":"Leoville",
    "gn:population":0,
    "gn:timezone":"Europe/Jersey",
    "iso:country":"JE",
    "name:fra_x_preferred":[
        "Leoville"
    ],
    "wof:name":"Leoville",
    "wof:placetype":"locality"
},
  "geometry": {"coordinates":[-2.20714,49.23828],"type":"Point"}
}