{
  "type": "Feature",
  "properties": {
    "gn:admin1_code":"3237072.0",
    "gn:asciiname":"Le Hocq",
    "gn:country_code":"JE",
    "gn:dem":11,
    "gn:feature_class":"P",
    "gn:feature_code":"PPLA",
    "gn:name":"Le Hocq",
    "gn:population":0,
    "gn:timezone":"Europe/Jersey",
    "iso:country":"JE",
    "wof:name":"Le Hocq",
    "wof:placetype":"locality"
},
  "geometry": {"coordinates":[-2.06178,49.16823],"type":"Point"}
}