{
  "type": "Feature",
  "properties": {
    "gn:asciiname":"Plemont",
    "gn:country_code":"JE",
    "gn:dem":65,
    "gn:feature_class":"P",
    "gn:feature_code":"PPL",
    "gn:name":"Plemont",
    "gn:population":0,
    "gn:timezone":"Europe/Jersey",
    "iso:country":"JE",
    "wof:name":"Plemont",
    "wof:placetype":"locality"
},
  "geometry": {"coordinates":[-2.22761,49.25666],"type":"Point"}
}