{
  "type": "Feature",
  "properties": {
    "gn:asciiname":"La Robeline",
    "gn:country_code":"JE",
    "gn:dem":61,
    "gn:feature_class":"P",
    "gn:feature_code":"PPL",
    "gn:name":"La Robeline",
    "gn:population":0,
    "gn:timezone":"Europe/Jersey",
    "iso:country":"JE",
    "wof:name":"La Robeline",
    "wof:placetype":"locality"
},
  "geometry": {"coordinates":[-2.22503,49.23593],"type":"Point"}
}