{
  "type": "Feature",
  "properties": {
    "gn:admin1_code":"0.0",
    "gn:asciiname":"La Ville au Bas",
    "gn:cc2":"GB",
    "gn:country_code":"JE",
    "gn:dem":67,
    "gn:feature_class":"P",
    "gn:feature_code":"PPL",
    "gn:name":"La Ville au Bas",
    "gn:population":0,
    "gn:timezone":"Europe/Jersey",
    "iso:country":"JE",
    "name:und_x_variant":[
        "Ville au Bas"
    ],
    "wof:name":"La Ville au Bas",
    "wof:placetype":"locality"
},
  "geometry": {"coordinates":[-2.21563,49.22766],"type":"Point"}
}