{
  "type": "Feature",
  "properties": {
    "gn:asciiname":"Les Labeurs",
    "gn:country_code":"JE",
    "gn:dem":5,
    "gn:feature_class":"P",
    "gn:feature_code":"PPL",
    "gn:name":"Les Labeurs",
    "gn:population":0,
    "gn:timezone":"Europe/Jersey",
    "iso:country":"JE",
    "wof:name":"Les Labeurs",
    "wof:placetype":"locality"
},
  "geometry": {"coordinates":[-2.234,49.22976],"type":"Point"}
}