{
  "type": "Feature",
  "properties": {
    "gn:admin1_code":"0.0",
    "gn:asciiname":"Longueville",
    "gn:country_code":"JE",
    "gn:dem":21,
    "gn:feature_class":"P",
    "gn:feature_code":"PPL",
    "gn:name":"Longueville",
    "gn:population":0,
    "gn:timezone":"Europe/Jersey",
    "iso:country":"JE",
    "name:eng_x_preferred":[
        "Longueville"
    ],
    "wof:name":"Longueville",
    "wof:placetype":"locality"
},
  "geometry": {"coordinates":[-2.08333,49.18333],"type":"Point"}
}