{
  "type": "Feature",
  "properties": {
    "iso:country":"JE",
    "qs_pg:aaroncc":"JE",
    "qs_pg:name":"St. Lawrence",
    "qs_pg:name_adm0":"United Kingdom",
    "qs_pg:name_adm1":"Channel Islands",
    "qs_pg:photos":647,
    "qs_pg:photos_1k":131,
    "qs_pg:photos_9k":6,
    "qs_pg:photos_9r":7,
    "qs_pg:photos_all":1430,
    "qs_pg:photos_sr":8,
    "qs_pg:pop_sr":0,
    "qs_pg:qs_pg_placetype":"localadmin",
    "qs_pg:qs_pg_placetype_gp":"LocalAdmin",
    "qs_pg:woe_adm0":23424975,
    "woe:adm0_id":23424975,
    "woe:name_adm0":"United Kingdom",
    "woe:name_adm1":"Channel Islands",
    "woe:placetype":"LocalAdmin",
    "wof:name":"St. Lawrence",
    "wof:placetype":"localadmin"
},
  "geometry": {"coordinates":[-2.141475,49.211093],"type":"Point"}
}